typedtsv/__init__.py
typedtsv/typedtsv.py
typedtsv-0.9.1.dist-info/LICENSE
typedtsv-0.9.1.dist-info/WHEEL
typedtsv-0.9.1.dist-info/METADATA
typedtsv-0.9.1.dist-info/RECORD
